Workbook

Sheet Income_Clean
A1: Metro Area | B1: Median Household Income | C1: Income Year
A2: Abilene, TX Metro Area | B2: 67328 | C2: 2024
A3: Aguadilla, PR Metro Area | B3: 22398 | C3: 2024
A4: Akron, OH Metro Area | B4: 72371 | C4: 2024
A5: Albany, GA Metro Area | B5: 56906 | C5: 2024
A6: Albany, OR Metro Area | B6: 76329 | C6: 2024
A7: Albany-Schenectady-Troy, NY Metro Area | B7: 88074 | C7: 2024
A8: Albuquerque, NM Metro Area | B8: 70783 | C8: 2024
A9: Alexandria, LA Metro Area | B9: 56353 | C9: 2024
A10: Allentown-Bethlehem-Easton, PA-NJ Metro Area | B10: 84587 | C10: 2024
A11: Altoona, PA Metro Area | B11: 62382 | C11: 2024
A12: Amarillo, TX Metro Area | B12: 69611 | C12: 2024
A13: Ames, IA Metro Area | B13: 73127 | C13: 2024
... A394: Yuma, AZ Metro Area | B394: 62876 | C394: 2024

Sheet Metro_Crosswalk
A1: Zillow Metro | B1: Census Metro | C1: Match Status | D1: Zillow City | E1: Census Match Candidate | F1: Zillow State | G1: Match Check
A2: York, PA | B2: York-Hanover, PA Metro Area | C2: Verified | D2: =LEFT(A2,FIND(",",A2)-1) -> York | E2: =IFERROR(INDEX(Census_Metro_List!$A:$A,MATCH(D2&"*",Census_Metro_List!$A:$A,0)),"No Match") -> York-Hanover, PA Metro Area | F2: =TRIM(RIGHT(A2,LEN(A2)-FIND(",",A2))) -> PA | G2: =IF(E2="No Match","Review",IF(ISNUMBER(SEARCH(F2,E2)),"Likely Match","Review")) -> Likely Match
A3: Philadelphia, PA | B3: Philadelphia-Camden-Wilmington, PA-NJ-DE-MD Metro Area | C3: Verified | D3: =LEFT(A3,FIND(",",A3)-1) -> Philadelphia | E3: =IFERROR(INDEX(Census_Metro_List!$A:$A,MATCH(D3&"*",Census_Metro_List!$A:$A,0)),"No Match") -> Philadelphia-Camden-Wilmington, PA-NJ-DE-MD Metro Area | F3: =TRIM(RIGHT(A3,LEN(A3)-FIND(",",A3))) -> PA | G3: =IF(E3="No Match","Review",IF(ISNUMBER(SEARCH(F3,E3)),"Likely Match","Review")) -> Likely Match
A4: Miami, FL | B4: Miami-Fort Lauderdale-West Palm Beach, FL Metro Area | C4: Verified | D4: =LEFT(A4,FIND(",",A4)-1) -> Miami | E4: =IFERROR(INDEX(Census_Metro_List!$A:$A,MATCH(D4&"*",Census_Metro_List!$A:$A,0)),"No Match") -> Miami-Fort Lauderdale-West Palm Beach, FL Metro Area | F4: =TRIM(RIGHT(A4,LEN(A4)-FIND(",",A4))) -> FL | G4: =IF(E4="No Match","Review",IF(ISNUMBER(SEARCH(F4,E4)),"Likely Match","Review")) -> Likely Match
A5: New York, NY | B5: New York-Newark-Jersey City, NY-NJ Metro Area | C5: Verified | D5: =LEFT(A5,FIND(",",A5)-1) -> New York | E5: =IFERROR(INDEX(Census_Metro_List!$A:$A,MATCH(D5&"*",Census_Metro_List!$A:$A,0)),"No Match") -> New York-Newark-Jersey City, NY-NJ Metro Area | F5: =TRIM(RIGHT(A5,LEN(A5)-FIND(",",A5))) -> NY | G5: =IF(E5="No Match","Review",IF(ISNUMBER(SEARCH(F5,E5)),"Likely Match","Review")) -> Likely Match
A6: Los Angeles, CA | B6: Los Angeles-Long Beach-Anaheim, CA Metro Area | C6: Verified | D6: =LEFT(A6,FIND(",",A6)-1) -> Los Angeles | E6: =IFERROR(INDEX(Census_Metro_List!$A:$A,MATCH(D6&"*",Census_Metro_List!$A:$A,0)),"No Match") -> Los Angeles-Long Beach-Anaheim, CA Metro Area | F6: =TRIM(RIGHT(A6,LEN(A6)-FIND(",",A6))) -> CA | G6: =IF(E6="No Match","Review",IF(ISNUMBER(SEARCH(F6,E6)),"Likely Match","Review")) -> Likely Match
A7: Chicago, IL | B7: Chicago-Naperville-Elgin, IL-IN Metro Area | C7: High Confidence | D7: =LEFT(A7,FIND(",",A7)-1) -> Chicago | E7: =IFERROR(INDEX(Census_Metro_List!$A:$A,MATCH(D7&"*",Census_Metro_List!$A:$A,0)),"No Match") -> Chicago-Naperville-Elgin, IL-IN Metro Area | F7: =TRIM(RIGHT(A7,LEN(A7)-FIND(",",A7))) -> IL | G7: =IF(E7="No Match","Review",IF(ISNUMBER(SEARCH(F7,E7)),"Likely Match","Review")) -> Likely Match
A8: Dallas, TX | B8: Dallas-Fort Worth-Arlington, TX Metro Area | C8: High Confidence | D8: =LEFT(A8,FIND(",",A8)-1) -> Dallas | E8: =IFERROR(INDEX(Census_Metro_List!$A:$A,MATCH(D8&"*",Census_Metro_List!$A:$A,0)),"No Match") -> Dallas-Fort Worth-Arlington, TX Metro Area | F8: =TRIM(RIGHT(A8,LEN(A8)-FIND(",",A8))) -> TX | G8: =IF(E8="No Match","Review",IF(ISNUMBER(SEARCH(F8,E8)),"Likely Match","Review")) -> Likely Match
A9: Houston, TX | B9: Houston-Pasadena-The Woodlands, TX Metro Area | C9: High Confidence | D9: =LEFT(A9,FIND(",",A9)-1) -> Houston | E9: =IFERROR(INDEX(Census_Metro_List!$A:$A,MATCH(D9&"*",Census_Metro_List!$A:$A,0)),"No Match") -> Houston-Pasadena-The Woodlands, TX Metro Area | F9: =TRIM(RIGHT(A9,LEN(A9)-FIND(",",A9))) -> TX | G9: =IF(E9="No Match","Review",IF(ISNUMBER(SEARCH(F9,E9)),"Likely Match","Review")) -> Likely Match
A10: Washington, DC | B10: Washington-Arlington-Alexandria, DC-VA-MD-WV Metro Area | C10: High Confidence | D10: =LEFT(A10,FIND(",",A10)-1) -> Washington | E10: =IFERROR(INDEX(Census_Metro_List!$A:$A,MATCH(D10&"*",Census_Metro_List!$A:$A,0)),"No Match") -> Washington-Arlington-Alexandria, DC-VA-MD-WV Metro Area | F10: =TRIM(RIGHT(A10,LEN(A10)-FIND(",",A10))) -> DC | G10: =IF(E10="No Match","Review",IF(ISNUMBER(SEARCH(F10,E10)),"Likely Match","Review")) -> Likely Match
A11: Atlanta, GA | B11: Atlanta-Sandy Springs-Roswell, GA Metro Area | C11: High Confidence | D11: =LEFT(A11,FIND(",",A11)-1) -> Atlanta | E11: =IFERROR(INDEX(Census_Metro_List!$A:$A,MATCH(D11&"*",Census_Metro_List!$A:$A,0)),"No Match") -> Atlanta-Sandy Springs-Roswell, GA Metro Area | F11: =TRIM(RIGHT(A11,LEN(A11)-FIND(",",A11))) -> GA | G11: =IF(E11="No Match","Review",IF(ISNUMBER(SEARCH(F11,E11)),"Likely Match","Review")) -> Likely Match
A12: Boston, MA | B12: Boston-Cambridge-Newton, MA-NH Metro Area | C12: High Confidence | D12: =LEFT(A12,FIND(",",A12)-1) -> Boston | E12: =IFERROR(INDEX(Census_Metro_List!$A:$A,MATCH(D12&"*",Census_Metro_List!$A:$A,0)),"No Match") -> Boston-Cambridge-Newton, MA-NH Metro Area | F12: =TRIM(RIGHT(A12,LEN(A12)-FIND(",",A12))) -> MA | G12: =IF(E12="No Match","Review",IF(ISNUMBER(SEARCH(F12,E12)),"Likely Match","Review")) -> Likely Match
A13: Phoenix, AZ | B13: Phoenix-Mesa-Chandler, AZ Metro Area | C13: High Confidence | D13: =LEFT(A13,FIND(",",A13)-1) -> Phoenix | E13: =IFERROR(INDEX(Census_Metro_List!$A:$A,MATCH(D13&"*",Census_Metro_List!$A:$A,0)),"No Match") -> Phoenix-Mesa-Chandler, AZ Metro Area | F13: =TRIM(RIGHT(A13,LEN(A13)-FIND(",",A13))) -> AZ | G13: =IF(E13="No Match","Review",IF(ISNUMBER(SEARCH(F13,E13)),"Likely Match","Review")) -> Likely Match
... A46: Richmond, VA | B46: Richmond, VA Metro Area | C46: High Confidence | D46: =LEFT(A46,FIND(",",A46)-1) -> Richmond | E46: =IFERROR(INDEX(Census_Metro_List!$A:$A,MATCH(D46&"*",Census_Metro_List!$A:$A,0)),"No Match") -> Richmond, VA Metro Area | F46: =TRIM(RIGHT(A46,LEN(A46)-FIND(",",A46))) -> VA | G46: =IF(E46="No Match","Review",IF(ISNUMBER(SEARCH(F46,E46)),"Likely Match","Review")) -> Likely Match
A47: Louisville, KY | C47: No Census Metro Match | D47: =LEFT(A47,FIND(",",A47)-1) -> Louisville | E47: =IFERROR(INDEX(Census_Metro_List!$A:$A,MATCH(D47&"*",Census_Metro_List!$A:$A,0)),"No Match") -> Louisville/Jefferson County, KY-IN Metro Area | F47: =TRIM(RIGHT(A47,LEN(A47)-FIND(",",A47))) -> KY | G47: =IF(E47="No Match","Review",IF(ISNUMBER(SEARCH(F47,E47)),"Likely Match","Review")) -> Likely Match
A48: New Orleans, LA | B48: New Orleans-Metairie, LA Metro Area | C48: High Confidence | D48: =LEFT(A48,FIND(",",A48)-1) -> New Orleans | E48: =IFERROR(INDEX(Census_Metro_List!$A:$A,MATCH(D48&"*",Census_Metro_List!$A:$A,0)),"No Match") -> New Orleans-Metairie, LA Metro Area | F48: =TRIM(RIGHT(A48,LEN(A48)-FIND(",",A48))) -> LA | G48: =IF(E48="No Match","Review",IF(ISNUMBER(SEARCH(F48,E48)),"Likely Match","Review")) -> Likely Match
A49: Salt Lake City, UT | B49: Salt Lake City-Murray, UT Metro Area | C49: High Confidence | D49: =LEFT(A49,FIND(",",A49)-1) -> Salt Lake City | E49: =IFERROR(INDEX(Census_Metro_List!$A:$A,MATCH(D49&"*",Census_Metro_List!$A:$A,0)),"No Match") -> Salt Lake City-Murray, UT Metro Area | F49: =TRIM(RIGHT(A49,LEN(A49)-FIND(",",A49))) -> UT | G49: =IF(E49="No Match","Review",IF(ISNUMBER(SEARCH(F49,E49)),"Likely Match","Review")) -> Likely Match
A50: Hartford, CT | B50: Hartford-West Hartford-East Hartford, CT Metro Area | C50: High Confidence | D50: =LEFT(A50,FIND(",",A50)-1) -> Hartford | E50: =IFERROR(INDEX(Census_Metro_List!$A:$A,MATCH(D50&"*",Census_Metro_List!$A:$A,0)),"No Match") -> Hartford-West Hartford-East Hartford, CT Metro Area | F50: =TRIM(RIGHT(A50,LEN(A50)-FIND(",",A50))) -> CT | G50: =IF(E50="No Match","Review",IF(ISNUMBER(SEARCH(F50,E50)),"Likely Match","Review")) -> Likely Match
A51: Buffalo, NY | B51: Buffalo-Cheektowaga, NY Metro Area | C51: High Confidence | D51: =LEFT(A51,FIND(",",A51)-1) -> Buffalo | E51: =IFERROR(INDEX(Census_Metro_List!$A:$A,MATCH(D51&"*",Census_Metro_List!$A:$A,0)),"No Match") -> Buffalo-Cheektowaga, NY Metro Area | F51: =TRIM(RIGHT(A51,LEN(A51)-FIND(",",A51))) -> NY | G51: =IF(E51="No Match","Review",IF(ISNUMBER(SEARCH(F51,E51)),"Likely Match","Review")) -> Likely Match
A52: Birmingham, AL | B52: Birmingham, AL Metro Area | C52: High Confidence | D52: =LEFT(A52,FIND(",",A52)-1) -> Birmingham | E52: =IFERROR(INDEX(Census_Metro_List!$A:$A,MATCH(D52&"*",Census_Metro_List!$A:$A,0)),"No Match") -> Birmingham, AL Metro Area | F52: =TRIM(RIGHT(A52,LEN(A52)-FIND(",",A52))) -> AL | G52: =IF(E52="No Match","Review",IF(ISNUMBER(SEARCH(F52,E52)),"Likely Match","Review")) -> Likely Match
A53: Rochester, NY | B53: Rochester, NY Metro Area | C53: High Confidence | D53: =LEFT(A53,FIND(",",A53)-1) -> Rochester | E53: =IFERROR(INDEX(Census_Metro_List!$A:$A,MATCH(D53&"*",Census_Metro_List!$A:$A,0)),"No Match") -> Rochester, MN Metro Area | F53: =TRIM(RIGHT(A53,LEN(A53)-FIND(",",A53))) -> NY | G53: =IF(E53="No Match","Review",IF(ISNUMBER(SEARCH(F53,E53)),"Likely Match","Review")) -> Review
A54: Grand Rapids, MI | B54: Grand Rapids-Wyoming-Kentwood, MI Metro Area | C54: High Confidence | D54: =LEFT(A54,FIND(",",A54)-1) -> Grand Rapids | E54: =IFERROR(INDEX(Census_Metro_List!$A:$A,MATCH(D54&"*",Census_Metro_List!$A:$A,0)),"No Match") -> Grand Rapids-Wyoming-Kentwood, MI Metro Area | F54: =TRIM(RIGHT(A54,LEN(A54)-FIND(",",A54))) -> MI | G54: =IF(E54="No Match","Review",IF(ISNUMBER(SEARCH(F54,E54)),"Likely Match","Review")) -> Likely Match
A55: Tucson, AZ | B55: Tucson, AZ Metro Area | C55: High Confidence | D55: =LEFT(A55,FIND(",",A55)-1) -> Tucson | E55: =IFERROR(INDEX(Census_Metro_List!$A:$A,MATCH(D55&"*",Census_Metro_List!$A:$A,0)),"No Match") -> Tucson, AZ Metro Area | F55: =TRIM(RIGHT(A55,LEN(A55)-FIND(",",A55))) -> AZ | G55: =IF(E55="No Match","Review",IF(ISNUMBER(SEARCH(F55,E55)),"Likely Match","Review")) -> Likely Match
A56: Urban Honolulu, HI | B56: Urban Honolulu, HI Metro Area | C56: High Confidence | D56: =LEFT(A56,FIND(",",A56)-1) -> Urban Honolulu | E56: =IFERROR(INDEX(Census_Metro_List!$A:$A,MATCH(D56&"*",Census_Metro_List!$A:$A,0)),"No Match") -> Urban Honolulu, HI Metro Area | F56: =TRIM(RIGHT(A56,LEN(A56)-FIND(",",A56))) -> HI | G56: =IF(E56="No Match","Review",IF(ISNUMBER(SEARCH(F56,E56)),"Likely Match","Review")) -> Likely Match
A57: Tulsa, OK | B57: Tulsa, OK Metro Area | C57: High Confidence | D57: =LEFT(A57,FIND(",",A57)-1) -> Tulsa | E57: =IFERROR(INDEX(Census_Metro_List!$A:$A,MATCH(D57&"*",Census_Metro_List!$A:$A,0)),"No Match") -> Tulsa, OK Metro Area | F57: =TRIM(RIGHT(A57,LEN(A57)-FIND(",",A57))) -> OK | G57: =IF(E57="No Match","Review",IF(ISNUMBER(SEARCH(F57,E57)),"Likely Match","Review")) -> Likely Match
A58: Fresno, CA | B58: Fresno, CA Metro Area | C58: High Confidence | D58: =LEFT(A58,FIND(",",A58)-1) -> Fresno | E58: =IFERROR(INDEX(Census_Metro_List!$A:$A,MATCH(D58&"*",Census_Metro_List!$A:$A,0)),"No Match") -> Fresno, CA Metro Area | F58: =TRIM(RIGHT(A58,LEN(A58)-FIND(",",A58))) -> CA | G58: =IF(E58="No Match","Review",IF(ISNUMBER(SEARCH(F58,E58)),"Likely Match","Review")) -> Likely Match
A59: Worcester, MA | B59: Worcester, MA Metro Area | C59: High Confidence | D59: =LEFT(A59,FIND(",",A59)-1) -> Worcester | E59: =IFERROR(INDEX(Census_Metro_List!$A:$A,MATCH(D59&"*",Census_Metro_List!$A:$A,0)),"No Match") -> Worcester, MA Metro Area | F59: =TRIM(RIGHT(A59,LEN(A59)-FIND(",",A59))) -> MA | G59: =IF(E59="No Match","Review",IF(ISNUMBER(SEARCH(F59,E59)),"Likely Match","Review")) -> Likely Match
... A222: Florence, SC | B222: Florence, SC Metro Area | C222: High Confidence | D222: =LEFT(A222,FIND(",",A222)-1) -> Florence | E222: =IFERROR(INDEX(Census_Metro_List!$A:$A,MATCH(D222&"*",Census_Metro_List!$A:$A,0)),"No Match") -> Florence, SC Metro Area | F222: =TRIM(RIGHT(A222,LEN(A222)-FIND(",",A222))) -> SC | G222: =IF(E222="No Match","Review",IF(ISNUMBER(SEARCH(F222,E222)),"Likely Match","Review")) -> Likely Match
A223: Hilo, HI | C223: No Census Metro Match | D223: =LEFT(A223,FIND(",",A223)-1) -> Hilo | E223: =IFERROR(INDEX(Census_Metro_List!$A:$A,MATCH(D223&"*",Census_Metro_List!$A:$A,0)),"No Match") -> No Match | F223: =TRIM(RIGHT(A223,LEN(A223)-FIND(",",A223))) -> HI | G223: =IF(E223="No Match","Review",IF(ISNUMBER(SEARCH(F223,E223)),"Likely Match","Review")) -> Review
A224: St. Cloud, MN | B224: St. Cloud, MN Metro Area | C224: High Confidence | D224: =LEFT(A224,FIND(",",A224)-1) -> St. Cloud | E224: =IFERROR(INDEX(Census_Metro_List!$A:$A,MATCH(D224&"*",Census_Metro_List!$A:$A,0)),"No Match") -> St. Cloud, MN Metro Area | F224: =TRIM(RIGHT(A224,LEN(A224)-FIND(",",A224))) -> MN | G224: =IF(E224="No Match","Review",IF(ISNUMBER(SEARCH(F224,E224)),"Likely Match","Review")) -> Likely Match
A225: Racine, WI | B225: Racine-Mount Pleasant, WI Metro Area | C225: High Confidence | D225: =LEFT(A225,FIND(",",A225)-1) -> Racine | E225: =IFERROR(INDEX(Census_Metro_List!$A:$A,MATCH(D225&"*",Census_Metro_List!$A:$A,0)),"No Match") -> Racine-Mount Pleasant, WI Metro Area | F225: =TRIM(RIGHT(A225,LEN(A225)-FIND(",",A225))) -> WI | G225: =IF(E225="No Match","Review",IF(ISNUMBER(SEARCH(F225,E225)),"Likely Match","Review")) -> Likely Match
A226: Bend, OR | B226: Bend, OR Metro Area | C226: High Confidence | D226: =LEFT(A226,FIND(",",A226)-1) -> Bend | E226: =IFERROR(INDEX(Census_Metro_List!$A:$A,MATCH(D226&"*",Census_Metro_List!$A:$A,0)),"No Match") -> Bend, OR Metro Area | F226: =TRIM(RIGHT(A226,LEN(A226)-FIND(",",A226))) -> OR | G226: =IF(E226="No Match","Review",IF(ISNUMBER(SEARCH(F226,E226)),"Likely Match","Review")) -> Likely Match
A227: Saginaw, MI | B227: Saginaw, MI Metro Area | C227: High Confidence | D227: =LEFT(A227,FIND(",",A227)-1) -> Saginaw | E227: =IFERROR(INDEX(Census_Metro_List!$A:$A,MATCH(D227&"*",Census_Metro_List!$A:$A,0)),"No Match") -> Saginaw, MI Metro Area | F227: =TRIM(RIGHT(A227,LEN(A227)-FIND(",",A227))) -> MI | G227: =IF(E227="No Match","Review",IF(ISNUMBER(SEARCH(F227,E227)),"Likely Match","Review")) -> Likely Match
A228: Warner Robins, GA | B228: Warner Robins, GA Metro Area | C228: High Confidence | D228: =LEFT(A228,FIND(",",A228)-1) -> Warner Robins | E228: =IFERROR(INDEX(Census_Metro_List!$A:$A,MATCH(D228&"*",Census_Metro_List!$A:$A,0)),"No Match") -> Warner Robins, GA Metro Area | F228: =TRIM(RIGHT(A228,LEN(A228)-FIND(",",A228))) -> GA | G228: =IF(E228="No Match","Review",IF(ISNUMBER(SEARCH(F228,E228)),"Likely Match","Review")) -> Likely Match
A229: Terre Haute, IN | B229: Terre Haute, IN Metro Area | C229: High Confidence | D229: =LEFT(A229,FIND(",",A229)-1) -> Terre Haute | E229: =IFERROR(INDEX(Census_Metro_List!$A:$A,MATCH(D229&"*",Census_Metro_List!$A:$A,0)),"No Match") -> Terre Haute, IN Metro Area | F229: =TRIM(RIGHT(A229,LEN(A229)-FIND(",",A229))) -> IN | G229: =IF(E229="No Match","Review",IF(ISNUMBER(SEARCH(F229,E229)),"Likely Match","Review")) -> Likely Match
A230: Torrington, CT | C230: No Census Metro Match | D230: =LEFT(A230,FIND(",",A230)-1) -> Torrington | E230: =IFERROR(INDEX(Census_Metro_List!$A:$A,MATCH(D230&"*",Census_Metro_List!$A:$A,0)),"No Match") -> No Match | F230: =TRIM(RIGHT(A230,LEN(A230)-FIND(",",A230))) -> CT | G230: =IF(E230="No Match","Review",IF(ISNUMBER(SEARCH(F230,E230)),"Likely Match","Review")) -> Review
A231: Punta Gorda, FL | B231: Punta Gorda, FL Metro Area | C231: High Confidence | D231: =LEFT(A231,FIND(",",A231)-1) -> Punta Gorda | E231: =IFERROR(INDEX(Census_Metro_List!$A:$A,MATCH(D231&"*",Census_Metro_List!$A:$A,0)),"No Match") -> Punta Gorda, FL Metro Area | F231: =TRIM(RIGHT(A231,LEN(A231)-FIND(",",A231))) -> FL | G231: =IF(E231="No Match","Review",IF(ISNUMBER(SEARCH(F231,E231)),"Likely Match","Review")) -> Likely Match
A232: Billings, MT | B232: Billings, MT Metro Area | C232: High Confidence | D232: =LEFT(A232,FIND(",",A232)-1) -> Billings | E232: =IFERROR(INDEX(Census_Metro_List!$A:$A,MATCH(D232&"*",Census_Metro_List!$A:$A,0)),"No Match") -> Billings, MT Metro Area | F232: =TRIM(RIGHT(A232,LEN(A232)-FIND(",",A232))) -> MT | G232: =IF(E232="No Match","Review",IF(ISNUMBER(SEARCH(F232,E232)),"Likely Match","Review")) -> Likely Match
A233: Redding, CA | B233: Redding, CA Metro Area | C233: High Confidence | D233: =LEFT(A233,FIND(",",A233)-1) -> Redding | E233: =IFERROR(INDEX(Census_Metro_List!$A:$A,MATCH(D233&"*",Census_Metro_List!$A:$A,0)),"No Match") -> Redding, CA Metro Area | F233: =TRIM(RIGHT(A233,LEN(A233)-FIND(",",A233))) -> CA | G233: =IF(E233="No Match","Review",IF(ISNUMBER(SEARCH(F233,E233)),"Likely Match","Review")) -> Likely Match
A234: Kingston, NY | B234: Kingston, NY Metro Area | C234: High Confidence | D234: =LEFT(A234,FIND(",",A234)-1) -> Kingston | E234: =IFERROR(INDEX(Census_Metro_List!$A:$A,MATCH(D234&"*",Census_Metro_List!$A:$A,0)),"No Match") -> Kingston, NY Metro Area | F234: =TRIM(RIGHT(A234,LEN(A234)-FIND(",",A234))) -> NY | G234: =IF(E234="No Match","Review",IF(ISNUMBER(SEARCH(F234,E234)),"Likely Match","Review")) -> Likely Match
A235: Panama City, FL | B235: Panama City-Panama City Beach, FL Metro Area | C235: High Confidence | D235: =LEFT(A235,FIND(",",A235)-1) -> Panama City | E235: =IFERROR(INDEX(Census_Metro_List!$A:$A,MATCH(D235&"*",Census_Metro_List!$A:$A,0)),"No Match") -> Panama City-Panama City Beach, FL Metro Area | F235: =TRIM(RIGHT(A235,LEN(A235)-FIND(",",A235))) -> FL | G235: =IF(E235="No Match","Review",IF(ISNUMBER(SEARCH(F235,E235)),"Likely Match","Review")) -> Likely Match
A236: Joplin, MO | B236: Joplin, MO-KS Metro Area | C236: High Confidence | D236: =LEFT(A236,FIND(",",A236)-1) -> Joplin | E236: =IFERROR(INDEX(Census_Metro_List!$A:$A,MATCH(D236&"*",Census_Metro_List!$A:$A,0)),"No Match") -> Joplin, MO-KS Metro Area | F236: =TRIM(RIGHT(A236,LEN(A236)-FIND(",",A236))) -> MO | G236: =IF(E236="No Match","Review",IF(ISNUMBER(SEARCH(F236,E236)),"Likely Match","Review")) -> Likely Match
A237: Dover, DE | B237: Dover, DE Metro Area | C237: High Confidence | D237: =LEFT(A237,FIND(",",A237)-1) -> Dover | E237: =IFERROR(INDEX(Census_Metro_List!$A:$A,MATCH(D237&"*",Census_Metro_List!$A:$A,0)),"No Match") -> Dover, DE Metro Area | F237: =TRIM(RIGHT(A237,LEN(A237)-FIND(",",A237))) -> DE | G237: =IF(E237="No Match","Review",IF(ISNUMBER(SEARCH(F237,E237)),"Likely Match","Review")) -> Likely Match
A238: El Centro, CA | B238: El Centro, CA Metro Area | C238: High Confidence | D238: =LEFT(A238,FIND(",",A238)-1) -> El Centro | E238: =IFERROR(INDEX(Census_Metro_List!$A:$A,MATCH(D238&"*",Census_Metro_List!$A:$A,0)),"No Match") -> El Centro, CA Metro Area | F238: =TRIM(RIGHT(A238,LEN(A238)-FIND(",",A238))) -> CA | G238: =IF(E238="No Match","Review",IF(ISNUMBER(SEARCH(F238,E238)),"Likely Match","Review")) -> Likely Match
A239: Jackson, TN | B239: Jackson, TN Metro Area | C239: High Confidence | D239: =LEFT(A239,FIND(",",A239)-1) -> Jackson | E239: =IFERROR(INDEX(Census_Metro_List!$A:$A,MATCH(D239&"*",Census_Metro_List!$A:$A,0)),"No Match") -> Jackson, MI Metro Area | F239: =TRIM(RIGHT(A239,LEN(A239)-FIND(",",A239))) -> TN | G239: =IF(E239="No Match","Review",IF(ISNUMBER(SEARCH(F239,E239)),"Likely Match","Review")) -> Review
A240: Yuba City, CA | B240: Yuba City, CA Metro Area | C240: High Confidence | D240: =LEFT(A240,FIND(",",A240)-1) -> Yuba City | E240: =IFERROR(INDEX(Census_Metro_List!$A:$A,MATCH(D240&"*",Census_Metro_List!$A:$A,0)),"No Match") -> Yuba City, CA Metro Area | F240: =TRIM(RIGHT(A240,LEN(A240)-FIND(",",A240))) -> CA | G240: =IF(E240="No Match","Review",IF(ISNUMBER(SEARCH(F240,E240)),"Likely Match","Review")) -> Likely Match
A241: Bowling Green, KY | B241: Bowling Green, KY Metro Area | C241: High Confidence | D241: =LEFT(A241,FIND(",",A241)-1) -> Bowling Green | E241: =IFERROR(INDEX(Census_Metro_List!$A:$A,MATCH(D241&"*",Census_Metro_List!$A:$A,0)),"No Match") -> Bowling Green, KY Metro Area | F241: =TRIM(RIGHT(A241,LEN(A241)-FIND(",",A241))) -> KY | G241: =IF(E241="No Match","Review",IF(ISNUMBER(SEARCH(F241,E241)),"Likely Match","Review")) -> Likely Match
A242: St. George, UT | B242: St. George, UT Metro Area | C242: High Confidence | D242: =LEFT(A242,FIND(",",A242)-1) -> St. George | E242: =IFERROR(INDEX(Census_Metro_List!$A:$A,MATCH(D242&"*",Census_Metro_List!$A:$A,0)),"No Match") -> St. George, UT Metro Area | F242: =TRIM(RIGHT(A242,LEN(A242)-FIND(",",A242))) -> UT | G242: =IF(E242="No Match","Review",IF(ISNUMBER(SEARCH(F242,E242)),"Likely Match","Review")) -> Likely Match
... A255: Coeur d'Alene, ID | B255: Coeur d'Alene, ID Metro Area | C255: High Confidence | D255: =LEFT(A255,FIND(",",A255)-1) -> Coeur d'Alene | E255: =IFERROR(INDEX(Census_Metro_List!$A:$A,MATCH(D255&"*",Census_Metro_List!$A:$A,0)),"No Match") -> Coeur d'Alene, ID Metro Area | F255: =TRIM(RIGHT(A255,LEN(A255)-FIND(",",A255))) -> ID | G255: =IF(E255="No Match","Review",IF(ISNUMBER(SEARCH(F255,E255)),"Likely Match","Review")) -> Likely Match
A256: East Stroudsburg, PA | C256: No Census Metro Match | D256: =LEFT(A256,FIND(",",A256)-1) -> East Stroudsburg | E256: =IFERROR(INDEX(Census_Metro_List!$A:$A,MATCH(D256&"*",Census_Metro_List!$A:$A,0)),"No Match") -> No Match | F256: =TRIM(RIGHT(A256,LEN(A256)-FIND(",",A256))) -> PA | G256: =IF(E256="No Match","Review",IF(ISNUMBER(SEARCH(F256,E256)),"Likely Match","Review")) -> Review
A257: Pueblo, CO | B257: Pueblo, CO Metro Area | C257: High Confidence | D257: =LEFT(A257,FIND(",",A257)-1) -> Pueblo | E257: =IFERROR(INDEX(Census_Metro_List!$A:$A,MATCH(D257&"*",Census_Metro_List!$A:$A,0)),"No Match") -> Pueblo, CO Metro Area | F257: =TRIM(RIGHT(A257,LEN(A257)-FIND(",",A257))) -> CO | G257: =IF(E257="No Match","Review",IF(ISNUMBER(SEARCH(F257,E257)),"Likely Match","Review")) -> Likely Match
A258: Blacksburg, VA | B258: Blacksburg-Christiansburg-Radford, VA Metro Area | C258: High Confidence | D258: =LEFT(A258,FIND(",",A258)-1) -> Blacksburg | E258: =IFERROR(INDEX(Census_Metro_List!$A:$A,MATCH(D258&"*",Census_Metro_List!$A:$A,0)),"No Match") -> Blacksburg-Christiansburg-Radford, VA Metro Area | F258: =TRIM(RIGHT(A258,LEN(A258)-FIND(",",A258))) -> VA | G258: =IF(E258="No Match","Review",IF(ISNUMBER(SEARCH(F258,E258)),"Likely Match","Review")) -> Likely Match
A259: Wausau, WI | B259: Wausau, WI Metro Area | C259: High Confidence | D259: =LEFT(A259,FIND(",",A259)-1) -> Wausau | E259: =IFERROR(INDEX(Census_Metro_List!$A:$A,MATCH(D259&"*",Census_Metro_List!$A:$A,0)),"No Match") -> Wausau, WI Metro Area | F259: =TRIM(RIGHT(A259,LEN(A259)-FIND(",",A259))) -> WI | G259: =IF(E259="No Match","Review",IF(ISNUMBER(SEARCH(F259,E259)),"Likely Match","Review")) -> Likely Match
A260: Kahului, HI | B260: Kahului-Wailuku, HI Metro Area | C260: High Confidence | D260: =LEFT(A260,FIND(",",A260)-1) -> Kahului | E260: =IFERROR(INDEX(Census_Metro_List!$A:$A,MATCH(D260&"*",Census_Metro_List!$A:$A,0)),"No Match") -> Kahului-Wailuku, HI Metro Area | F260: =TRIM(RIGHT(A260,LEN(A260)-FIND(",",A260))) -> HI | G260: =IF(E260="No Match","Review",IF(ISNUMBER(SEARCH(F260,E260)),"Likely Match","Review")) -> Likely Match
A261: Janesville, WI | B261: Janesville-Beloit, WI Metro Area | C261: High Confidence | D261: =LEFT(A261,FIND(",",A261)-1) -> Janesville | E261: =IFERROR(INDEX(Census_Metro_List!$A:$A,MATCH(D261&"*",Census_Metro_List!$A:$A,0)),"No Match") -> Janesville-Beloit, WI Metro Area | F261: =TRIM(RIGHT(A261,LEN(A261)-FIND(",",A261))) -> WI | G261: =IF(E261="No Match","Review",IF(ISNUMBER(SEARCH(F261,E261)),"Likely Match","Review")) -> Likely Match
A262: Tupelo, MS | C262: No Census Metro Match | D262: =LEFT(A262,FIND(",",A262)-1) -> Tupelo | E262: =IFERROR(INDEX(Census_Metro_List!$A:$A,MATCH(D262&"*",Census_Metro_List!$A:$A,0)),"No Match") -> No Match | F262: =TRIM(RIGHT(A262,LEN(A262)-FIND(",",A262))) -> MS | G262: =IF(E262="No Match","Review",IF(ISNUMBER(SEARCH(F262,E262)),"Likely Match","Review")) -> Review
A263: Bloomington, IN | B263: Bloomington, IN Metro Area | C263: High Confidence | D263: =LEFT(A263,FIND(",",A263)-1) -> Bloomington | E263: =IFERROR(INDEX(Census_Metro_List!$A:$A,MATCH(D263&"*",Census_Metro_List!$A:$A,0)),"No Match") -> Bloomington, IL Metro Area | F263: =TRIM(RIGHT(A263,LEN(A263)-FIND(",",A263))) -> IN | G263: =IF(E263="No Match","Review",IF(ISNUMBER(SEARCH(F263,E263)),"Likely Match","Review")) -> Likely Match
A264: Odessa, TX | B264: Odessa, TX Metro Area | C264: High Confidence | D264: =LEFT(A264,FIND(",",A264)-1) -> Odessa | E264: =IFERROR(INDEX(Census_Metro_List!$A:$A,MATCH(D264&"*",Census_Metro_List!$A:$A,0)),"No Match") -> Odessa, TX Metro Area | F264: =TRIM(RIGHT(A264,LEN(A264)-FIND(",",A264))) -> TX | G264: =IF(E264="No Match","Review",IF(ISNUMBER(SEARCH(F264,E264)),"Likely Match","Review")) -> Likely Match
A265: Jackson, MI | B265: Jackson, MI Metro Area | C265: High Confidence | D265: =LEFT(A265,FIND(",",A265)-1) -> Jackson | E265: =IFERROR(INDEX(Census_Metro_List!$A:$A,MATCH(D265&"*",Census_Metro_List!$A:$A,0)),"No Match") -> Jackson, MI Metro Area | F265: =TRIM(RIGHT(A265,LEN(A265)-FIND(",",A265))) -> MI | G265: =IF(E265="No Match","Review",IF(ISNUMBER(SEARCH(F265,E265)),"Likely Match","Review")) -> Likely Match
A266: State College, PA | B266: State College, PA Metro Area | C266: High Confidence | D266: =LEFT(A266,FIND(",",A266)-1) -> State College | E266: =IFERROR(INDEX(Census_Metro_List!$A:$A,MATCH(D266&"*",Census_Metro_List!$A:$A,0)),"No Match") -> State College, PA Metro Area | F266: =TRIM(RIGHT(A266,LEN(A266)-FIND(",",A266))) -> PA | G266: =IF(E266="No Match","Review",IF(ISNUMBER(SEARCH(F266,E266)),"Likely Match","Review")) -> Likely Match
A267: Sebastian, FL | B267: Sebastian-Vero Beach-West Vero Corridor, FL Metro Area | C267: High Confidence | D267: =LEFT(A267,FIND(",",A267)-1) -> Sebastian | E267: =IFERROR(INDEX(Census_Metro_List!$A:$A,MATCH(D267&"*",Census_Metro_List!$A:$A,0)),"No Match") -> Sebastian-Vero Beach-West Vero Corridor, FL Metro Area | F267: =TRIM(RIGHT(A267,LEN(A267)-FIND(",",A267))) -> FL | G267: =IF(E267="No Match","Review",IF(ISNUMBER(SEARCH(F267,E267)),"Likely Match","Review")) -> Likely Match
A268: Madera, CA | C268: No Census Metro Match | D268: =LEFT(A268,FIND(",",A268)-1) -> Madera | E268: =IFERROR(INDEX(Census_Metro_List!$A:$A,MATCH(D268&"*",Census_Metro_List!$A:$A,0)),"No Match") -> No Match | F268: =TRIM(RIGHT(A268,LEN(A268)-FIND(",",A268))) -> CA | G268: =IF(E268="No Match","Review",IF(ISNUMBER(SEARCH(F268,E268)),"Likely Match","Review")) -> Review
A269: Decatur, AL | B269: Decatur, AL Metro Area | C269: High Confidence | D269: =LEFT(A269,FIND(",",A269)-1) -> Decatur | E269: =IFERROR(INDEX(Census_Metro_List!$A:$A,MATCH(D269&"*",Census_Metro_List!$A:$A,0)),"No Match") -> Decatur, AL Metro Area | F269: =TRIM(RIGHT(A269,LEN(A269)-FIND(",",A269))) -> AL | G269: =IF(E269="No Match","Review",IF(ISNUMBER(SEARCH(F269,E269)),"Likely Match","Review")) -> Likely Match
A270: Chambersburg, PA | B270: Chambersburg, PA Metro Area | C270: High Confidence | D270: =LEFT(A270,FIND(",",A270)-1) -> Chambersburg | E270: =IFERROR(INDEX(Census_Metro_List!$A:$A,MATCH(D270&"*",Census_Metro_List!$A:$A,0)),"No Match") -> Chambersburg, PA Metro Area | F270: =TRIM(RIGHT(A270,LEN(A270)-FIND(",",A270))) -> PA | G270: =IF(E270="No Match","Review",IF(ISNUMBER(SEARCH(F270,E270)),"Likely Match","Review")) -> Likely Match
A271: Vineland, NJ | B271: Vineland, NJ Metro Area | C271: High Confidence | D271: =LEFT(A271,FIND(",",A271)-1) -> Vineland | E271: =IFERROR(INDEX(Census_Metro_List!$A:$A,MATCH(D271&"*",Census_Metro_List!$A:$A,0)),"No Match") -> Vineland, NJ Metro Area | F271: =TRIM(RIGHT(A271,LEN(A271)-FIND(",",A271))) -> NJ | G271: =IF(E271="No Match","Review",IF(ISNUMBER(SEARCH(F271,E271)),"Likely Match","Review")) -> Likely Match
A272: Idaho Falls, ID | B272: Idaho Falls, ID Metro Area | C272: High Confidence | D272: =LEFT(A272,FIND(",",A272)-1) -> Idaho Falls | E272: =IFERROR(INDEX(Census_Metro_List!$A:$A,MATCH(D272&"*",Census_Metro_List!$A:$A,0)),"No Match") -> Idaho Falls, ID Metro Area | F272: =TRIM(RIGHT(A272,LEN(A272)-FIND(",",A272))) -> ID | G272: =IF(E272="No Match","Review",IF(ISNUMBER(SEARCH(F272,E272)),"Likely Match","Review")) -> Likely Match
A273: Grand Junction, CO | B273: Grand Junction, CO Metro Area | C273: High Confidence | D273: =LEFT(A273,FIND(",",A273)-1) -> Grand Junction | E273: =IFERROR(INDEX(Census_Metro_List!$A:$A,MATCH(D273&"*",Census_Metro_List!$A:$A,0)),"No Match") -> Grand Junction, CO Metro Area | F273: =TRIM(RIGHT(A273,LEN(A273)-FIND(",",A273))) -> CO | G273: =IF(E273="No Match","Review",IF(ISNUMBER(SEARCH(F273,E273)),"Likely Match","Review")) -> Likely Match
A274: Elizabethtown, KY | B274: Elizabethtown, KY Metro Area | C274: High Confidence | D274: =LEFT(A274,FIND(",",A274)-1) -> Elizabethtown | E274: =IFERROR(INDEX(Census_Metro_List!$A:$A,MATCH(D274&"*",Census_Metro_List!$A:$A,0)),"No Match") -> Elizabethtown, KY Metro Area | F274: =TRIM(RIGHT(A274,LEN(A274)-FIND(",",A274))) -> KY | G274: =IF(E274="No Match","Review",IF(ISNUMBER(SEARCH(F274,E274)),"Likely Match","Review")) -> Likely Match
A275: Niles, MI | B275: Niles, MI Metro Area | C275: High Confidence | D275: =LEFT(A275,FIND(",",A275)-1) -> Niles | E275: =IFERROR(INDEX(Census_Metro_List!$A:$A,MATCH(D275&"*",Census_Metro_List!$A:$A,0)),"No Match") -> Niles, MI Metro Area | F275: =TRIM(RIGHT(A275,LEN(A275)-FIND(",",A275))) -> MI | G275: =IF(E275="No Match","Review",IF(ISNUMBER(SEARCH(F275,E275)),"Likely Match","Review")) -> Likely Match
A276: Monroe, MI | B276: Monroe, MI Metro Area | C276: High Confidence | D276: =LEFT(A276,FIND(",",A276)-1) -> Monroe | E276: =IFERROR(INDEX(Census_Metro_List!$A:$A,MATCH(D276&"*",Census_Metro_List!$A:$A,0)),"No Match") -> Monroe, LA Metro Area | F276: =TRIM(RIGHT(A276,LEN(A276)-FIND(",",A276))) -> MI | G276: =IF(E276="No Match","Review",IF(ISNUMBER(SEARCH(F276,E276)),"Likely Match","Review")) -> Review
A277: Santa Fe, NM | B277: Santa Fe, NM Metro Area | C277: High Confidence | D277: =LEFT(A277,FIND(",",A277)-1) -> Santa Fe | E277: =IFERROR(INDEX(Census_Metro_List!$A:$A,MATCH(D277&"*",Census_Metro_List!$A:$A,0)),"No Match") -> Santa Fe, NM Metro Area | F277: =TRIM(RIGHT(A277,LEN(A277)-FIND(",",A277))) -> NM | G277: =IF(E277="No Match","Review",IF(ISNUMBER(SEARCH(F277,E277)),"Likely Match","Review")) -> Likely Match
A278: Concord, NH | C278: No Census Metro Match | D278: =LEFT(A278,FIND(",",A278)-1) -> Concord | E278: =IFERROR(INDEX(Census_Metro_List!$A:$A,MATCH(D278&"*",Census_Metro_List!$A:$A,0)),"No Match") -> No Match | F278: =TRIM(RIGHT(A278,LEN(A278)-FIND(",",A278))) -> NH | G278: =IF(E278="No Match","Review",IF(ISNUMBER(SEARCH(F278,E278)),"Likely Match","Review")) -> Review
A279: Alexandria, LA | B279: Alexandria, LA Metro Area | C279: High Confidence | D279: =LEFT(A279,FIND(",",A279)-1) -> Alexandria | E279: =IFERROR(INDEX(Census_Metro_List!$A:$A,MATCH(D279&"*",Census_Metro_List!$A:$A,0)),"No Match") -> Alexandria, LA Metro Area | F279: =TRIM(RIGHT(A279,LEN(A279)-FIND(",",A279))) -> LA | G279: =IF(E279="No Match","Review",IF(ISNUMBER(SEARCH(F279,E279)),"Likely Match","Review")) -> Likely Match
A280: Traverse City, MI | B280: Traverse City, MI Metro Area | C280: High Confidence | D280: =LEFT(A280,FIND(",",A280)-1) -> Traverse City | E280: =IFERROR(INDEX(Census_Metro_List!$A:$A,MATCH(D280&"*",Census_Metro_List!$A:$A,0)),"No Match") -> Traverse City, MI Metro Area | F280: =TRIM(RIGHT(A280,LEN(A280)-FIND(",",A280))) -> MI | G280: =IF(E280="No Match","Review",IF(ISNUMBER(SEARCH(F280,E280)),"Likely Match","Review")) -> Likely Match
A281: Bangor, ME | B281: Bangor, ME Metro Area | C281: High Confidence | D281: =LEFT(A281,FIND(",",A281)-1) -> Bangor | E281: =IFERROR(INDEX(Census_Metro_List!$A:$A,MATCH(D281&"*",Census_Metro_List!$A:$A,0)),"No Match") -> Bangor, ME Metro Area | F281: =TRIM(RIGHT(A281,LEN(A281)-FIND(",",A281))) -> ME | G281: =IF(E281="No Match","Review",IF(ISNUMBER(SEARCH(F281,E281)),"Likely Match","Review")) -> Likely Match
A282: Homosassa Springs, FL | B282: Homosassa Springs, FL Metro Area | C282: High Confidence | D282: =LEFT(A282,FIND(",",A282)-1) -> Homosassa Springs | E282: =IFERROR(INDEX(Census_Metro_List!$A:$A,MATCH(D282&"*",Census_Metro_List!$A:$A,0)),"No Match") -> Homosassa Springs, FL Metro Area | F282: =TRIM(RIGHT(A282,LEN(A282)-FIND(",",A282))) -> FL | G282: =IF(E282="No Match","Review",IF(ISNUMBER(SEARCH(F282,E282)),"Likely Match","Review")) -> Likely Match
A283: Hanford, CA | B283: Hanford-Corcoran, CA Metro Area | C283: High Confidence | D283: =LEFT(A283,FIND(",",A283)-1) -> Hanford | E283: =IFERROR(INDEX(Census_Metro_List!$A:$A,MATCH(D283&"*",Census_Metro_List!$A:$A,0)),"No Match") -> Hanford-Corcoran, CA Metro Area | F283: =TRIM(RIGHT(A283,LEN(A283)-FIND(",",A283))) -> CA | G283: =IF(E283="No Match","Review",IF(ISNUMBER(SEARCH(F283,E283)),"Likely Match","Review")) -> Likely Match
A284: Jefferson City, MO | B284: Jefferson City, MO Metro Area | C284: High Confidence | D284: =LEFT(A284,FIND(",",A284)-1) -> Jefferson City | E284: =IFERROR(INDEX(Census_Metro_List!$A:$A,MATCH(D284&"*",Census_Metro_List!$A:$A,0)),"No Match") -> Jefferson City, MO Metro Area | F284: =TRIM(RIGHT(A284,LEN(A284)-FIND(",",A284))) -> MO | G284: =IF(E284="No Match","Review",IF(ISNUMBER(SEARCH(F284,E284)),"Likely Match","Review")) -> Likely Match
A285: Florence, AL | B285: Florence-Muscle Shoals, AL Metro Area | C285: High Confidence | D285: =LEFT(A285,FIND(",",A285)-1) -> Florence | E285: =IFERROR(INDEX(Census_Metro_List!$A:$A,MATCH(D285&"*",Census_Metro_List!$A:$A,0)),"No Match") -> Florence, SC Metro Area | F285: =TRIM(RIGHT(A285,LEN(A285)-FIND(",",A285))) -> AL | G285: =IF(E285="No Match","Review",IF(ISNUMBER(SEARCH(F285,E285)),"Likely Match","Review")) -> Review
A286: Dothan, AL | B286: Dothan, AL Metro Area | C286: High Confidence | D286: =LEFT(A286,FIND(",",A286)-1) -> Dothan | E286: =IFERROR(INDEX(Census_Metro_List!$A:$A,MATCH(D286&"*",Census_Metro_List!$A:$A,0)),"No Match") -> Dothan, AL Metro Area | F286: =TRIM(RIGHT(A286,LEN(A286)-FIND(",",A286))) -> AL | G286: =IF(E286="No Match","Review",IF(ISNUMBER(SEARCH(F286,E286)),"Likely Match","Review")) -> Likely Match
A287: London, KY | C287: No Census Metro Match | D287: =LEFT(A287,FIND(",",A287)-1) -> London | E287: =IFERROR(INDEX(Census_Metro_List!$A:$A,MATCH(D287&"*",Census_Metro_List!$A:$A,0)),"No Match") -> No Match | F287: =TRIM(RIGHT(A287,LEN(A287)-FIND(",",A287))) -> KY | G287: =IF(E287="No Match","Review",IF(ISNUMBER(SEARCH(F287,E287)),"Likely Match","Review")) -> Review
A288: Albany, GA | B288: Albany, GA Metro Area | C288: High Confidence | D288: =LEFT(A288,FIND(",",A288)-1) -> Albany | E288: =IFERROR(INDEX(Census_Metro_List!$A:$A,MATCH(D288&"*",Census_Metro_List!$A:$A,0)),"No Match") -> Albany, GA Metro Area | F288: =TRIM(RIGHT(A288,LEN(A288)-FIND(",",A288))) -> GA | G288: =IF(E288="No Match","Review",IF(ISNUMBER(SEARCH(F288,E288)),"Likely Match","Review")) -> Likely Match
A289: Sioux City, IA | B289: Sioux City, IA-NE-SD Metro Area | C289: High Confidence | D289: =LEFT(A289,FIND(",",A289)-1) -> Sioux City | E289: =IFERROR(INDEX(Census_Metro_List!$A:$A,MATCH(D289&"*",Census_Metro_List!$A:$A,0)),"No Match") -> Sioux City, IA-NE-SD Metro Area | F289: =TRIM(RIGHT(A289,LEN(A289)-FIND(",",A289))) -> IA | G289: =IF(E289="No Match","Review",IF(ISNUMBER(SEARCH(F289,E289)),"Likely Match","Review")) -> Likely Match
A290: Wichita Falls, TX | B290: Wichita Falls, TX Metro Area | C290: High Confidence | D290: =LEFT(A290,FIND(",",A290)-1) -> Wichita Falls | E290: =IFERROR(INDEX(Census_Metro_List!$A:$A,MATCH(D290&"*",Census_Metro_List!$A:$A,0)),"No Match") -> Wichita Falls, TX Metro Area | F290: =TRIM(RIGHT(A290,LEN(A290)-FIND(",",A290))) -> TX | G290: =IF(E290="No Match","Review",IF(ISNUMBER(SEARCH(F290,E290)),"Likely Match","Review")) -> Likely Match
A291: Texarkana, TX | B291: Texarkana, TX-AR Metro Area | C291: High Confidence | D291: =LEFT(A291,FIND(",",A291)-1) -> Texarkana | E291: =IFERROR(INDEX(Census_Metro_List!$A:$A,MATCH(D291&"*",Census_Metro_List!$A:$A,0)),"No Match") -> Texarkana, TX-AR Metro Area | F291: =TRIM(RIGHT(A291,LEN(A291)-FIND(",",A291))) -> TX | G291: =IF(E291="No Match","Review",IF(ISNUMBER(SEARCH(F291,E291)),"Likely Match","Review")) -> Likely Match
A292: Valdosta, GA | B292: Valdosta, GA Metro Area | C292: High Confidence | D292: =LEFT(A292,FIND(",",A292)-1) -> Valdosta | E292: =IFERROR(INDEX(Census_Metro_List!$A:$A,MATCH(D292&"*",Census_Metro_List!$A:$A,0)),"No Match") -> Valdosta, GA Metro Area | F292: =TRIM(RIGHT(A292,LEN(A292)-FIND(",",A292))) -> GA | G292: =IF(E292="No Match","Review",IF(ISNUMBER(SEARCH(F292,E292)),"Likely Match","Review")) -> Likely Match
A293: Logan, UT | B293: Logan, UT-ID Metro Area | C293: High Confidence | D293: =LEFT(A293,FIND(",",A293)-1) -> Logan | E293: =IFERROR(INDEX(Census_Metro_List!$A:$A,MATCH(D293&"*",Census_Metro_List!$A:$A,0)),"No Match") -> Logan, UT-ID Metro Area | F293: =TRIM(RIGHT(A293,LEN(A293)-FIND(",",A293))) -> UT | G293: =IF(E293="No Match","Review",IF(ISNUMBER(SEARCH(F293,E293)),"Likely Match","Review")) -> Likely Match
A294: Flagstaff, AZ | B294: Flagstaff, AZ Metro Area | C294: High Confidence | D294: =LEFT(A294,FIND(",",A294)-1) -> Flagstaff | E294: =IFERROR(INDEX(Census_Metro_List!$A:$A,MATCH(D294&"*",Census_Metro_List!$A:$A,0)),"No Match") -> Flagstaff, AZ Metro Area | F294: =TRIM(RIGHT(A294,LEN(A294)-FIND(",",A294))) -> AZ | G294: =IF(E294="No Match","Review",IF(ISNUMBER(SEARCH(F294,E294)),"Likely Match","Review")) -> Likely Match
A295: Rocky Mount, NC | B295: Rocky Mount, NC Metro Area | C295: High Confidence | D295: =LEFT(A295,FIND(",",A295)-1) -> Rocky Mount | E295: =IFERROR(INDEX(Census_Metro_List!$A:$A,MATCH(D295&"*",Census_Metro_List!$A:$A,0)),"No Match") -> Rocky Mount, NC Metro Area | F295: =TRIM(RIGHT(A295,LEN(A295)-FIND(",",A295))) -> NC | G295: =IF(E295="No Match","Review",IF(ISNUMBER(SEARCH(F295,E295)),"Likely Match","Review")) -> Likely Match
A296: Pottsville, PA | C296: No Census Metro Match | D296: =LEFT(A296,FIND(",",A296)-1) -> Pottsville | E296: =IFERROR(INDEX(Census_Metro_List!$A:$A,MATCH(D296&"*",Census_Metro_List!$A:$A,0)),"No Match") -> No Match | F296: =TRIM(RIGHT(A296,LEN(A296)-FIND(",",A296))) -> PA | G296: =IF(E296="No Match","Review",IF(ISNUMBER(SEARCH(F296,E296)),"Likely Match","Review")) -> Review
A297: Dalton, GA | B297: Dalton, GA Metro Area | C297: High Confidence | D297: =LEFT(A297,FIND(",",A297)-1) -> Dalton | E297: =IFERROR(INDEX(Census_Metro_List!$A:$A,MATCH(D297&"*",Census_Metro_List!$A:$A,0)),"No Match") -> Dalton, GA Metro Area | F297: =TRIM(RIGHT(A297,LEN(A297)-FIND(",",A297))) -> GA | G297: =IF(E297="No Match","Review",IF(ISNUMBER(SEARCH(F297,E297)),"Likely Match","Review")) -> Likely Match
A298: Lebanon, PA | B298: Lebanon, PA Metro Area | C298: High Confidence | D298: =LEFT(A298,FIND(",",A298)-1) -> Lebanon | E298: =IFERROR(INDEX(Census_Metro_List!$A:$A,MATCH(D298&"*",Census_Metro_List!$A:$A,0)),"No Match") -> Lebanon, PA Metro Area | F298: =TRIM(RIGHT(A298,LEN(A298)-FIND(",",A298))) -> PA | G298: =IF(E298="No Match","Review",IF(ISNUMBER(SEARCH(F298,E298)),"Likely Match","Review")) -> Likely Match
A299: Morristown, TN | B299: Morristown, TN Metro Area | C299: High Confidence | D299: =LEFT(A299,FIND(",",A299)-1) -> Morristown | E299: =IFERROR(INDEX(Census_Metro_List!$A:$A,MATCH(D299&"*",Census_Metro_List!$A:$A,0)),"No Match") -> Morristown, TN Metro Area | F299: =TRIM(RIGHT(A299,LEN(A299)-FIND(",",A299))) -> TN | G299: =IF(E299="No Match","Review",IF(ISNUMBER(SEARCH(F299,E299)),"Likely Match","Review")) -> Likely Match
A300: Winchester, VA | B300: Winchester, VA-WV Metro Area | C300: High Confidence | D300: =LEFT(A300,FIND(",",A300)-1) -> Winchester | E300: =IFERROR(INDEX(Census_Metro_List!$A:$A,MATCH(D300&"*",Census_Metro_List!$A:$A,0)),"No Match") -> Winchester, VA-WV Metro Area | F300: =TRIM(RIGHT(A300,LEN(A300)-FIND(",",A300))) -> VA | G300: =IF(E300="No Match","Review",IF(ISNUMBER(SEARCH(F300,E300)),"Likely Match","Review")) -> Likely Match
A301: Wheeling, WV | B301: Wheeling, WV-OH Metro Area | C301: High Confidence | D301: =LEFT(A301,FIND(",",A301)-1) -> Wheeling | E301: =IFERROR(INDEX(Census_Metro_List!$A:$A,MATCH(D301&"*",Census_Metro_List!$A:$A,0)),"No Match") -> Wheeling, WV-OH Metro Area | F301: =TRIM(RIGHT(A301,LEN(A301)-FIND(",",A301))) -> WV | G301: =IF(E301="No Match","Review",IF(ISNUMBER(SEARCH(F301,E301)),"Likely Match","Review")) -> Likely Match
A302: Morgantown, WV | B302: Morgantown, WV Metro Area | C302: High Confidence | D302: =LEFT(A302,FIND(",",A302)-1) -> Morgantown | E302: =IFERROR(INDEX(Census_Metro_List!$A:$A,MATCH(D302&"*",Census_Metro_List!$A:$A,0)),"No Match") -> Morgantown, WV Metro Area | F302: =TRIM(RIGHT(A302,LEN(A302)-FIND(",",A302))) -> WV | G302: =IF(E302="No Match","Review",IF(ISNUMBER(SEARCH(F302,E302)),"Likely Match","Review")) -> Likely Match
A303: La Crosse, WI | B303: La Crosse-Onalaska, WI-MN Metro Area | C303: High Confidence | D303: =LEFT(A303,FIND(",",A303)-1) -> La Crosse | E303: =IFERROR(INDEX(Census_Metro_List!$A:$A,MATCH(D303&"*",Census_Metro_List!$A:$A,0)),"No Match") -> La Crosse-Onalaska, WI-MN Metro Area | F303: =TRIM(RIGHT(A303,LEN(A303)-FIND(",",A303))) -> WI | G303: =IF(E303="No Match","Review",IF(ISNUMBER(SEARCH(F303,E303)),"Likely Match","Review")) -> Likely Match
A304: Napa, CA | B304: Napa, CA Metro Area | C304: High Confidence | D304: =LEFT(A304,FIND(",",A304)-1) -> Napa | E304: =IFERROR(INDEX(Census_Metro_List!$A:$A,MATCH(D304&"*",Census_Metro_List!$A:$A,0)),"No Match") -> Napa, CA Metro Area | F304: =TRIM(RIGHT(A304,LEN(A304)-FIND(",",A304))) -> CA | G304: =IF(E304="No Match","Review",IF(ISNUMBER(SEARCH(F304,E304)),"Likely Match","Review")) -> Likely Match
A305: Rapid City, SD | B305: Rapid City, SD Metro Area | C305: High Confidence | D305: =LEFT(A305,FIND(",",A305)-1) -> Rapid City | E305: =IFERROR(INDEX(Census_Metro_List!$A:$A,MATCH(D305&"*",Census_Metro_List!$A:$A,0)),"No Match") -> Rapid City, SD Metro Area | F305: =TRIM(RIGHT(A305,LEN(A305)-FIND(",",A305))) -> SD | G305: =IF(E305="No Match","Review",IF(ISNUMBER(SEARCH(F305,E305)),"Likely Match","Review")) -> Likely Match
A306: Sumter, SC | B306: Sumter, SC Metro Area | C306: High Confidence | D306: =LEFT(A306,FIND(",",A306)-1) -> Sumter | E306: =IFERROR(INDEX(Census_Metro_List!$A:$A,MATCH(D306&"*",Census_Metro_List!$A:$A,0)),"No Match") -> Sumter, SC Metro Area | F306: =TRIM(RIGHT(A306,LEN(A306)-FIND(",",A306))) -> SC | G306: =IF(E306="No Match","Review",IF(ISNUMBER(SEARCH(F306,E306)),"Likely Match","Review")) -> Likely Match
...

Sheet Census_Metro_List
A1: Census Metro
A2: Abilene, TX Metro Area
A3: Aguadilla, PR Metro Area
A4: Akron, OH Metro Area
A5: Albany, GA Metro Area
A6: Albany, OR Metro Area
A7: Albany-Schenectady-Troy, NY Metro Area
A8: Albuquerque, NM Metro Area
A9: Alexandria, LA Metro Area
A10: Allentown-Bethlehem-Easton, PA-NJ Metro Area
A11: Altoona, PA Metro Area
A12: Amarillo, TX Metro Area
... A394: Yuma, AZ Metro Area

Sheet Census_Unmatched
A1: Census Metro | B1: Suggested Zillow Candidate | C1: Review Note
A2: Aguadilla, PR Metro Area | C2: No reliable Zillow alias found
A3: Amherst Town-Northampton, MA Metro Area | C3: No reliable Zillow alias found
A4: Arecibo, PR Metro Area | C4: No reliable Zillow alias found
A5: Dayton-Kettering-Beavercreek, OH Metro Area | C5: No reliable Zillow alias found
A6: Guayama, PR Metro Area | C6: No reliable Zillow alias found
A7: Kenosha, WI Metro Area | C7: No reliable Zillow alias found
A8: Kiryas Joel-Poughkeepsie-Newburgh, NY Metro Area | C8: No reliable Zillow alias found
A9: Lexington Park, MD Metro Area | C9: No reliable Zillow alias found
A10: Louisville/Jefferson County, KY-IN Metro Area | B10: Louisville, KY | C10: Strong alias candidate — verify
A11: Mayagüez, PR Metro Area | C11: No reliable Zillow alias found
A12: Ponce, PR Metro Area | C12: No reliable Zillow alias found
A13: Prescott Valley-Prescott, AZ Metro Area | C13: No reliable Zillow alias found
A14: San Juan-Bayamón-Caguas, PR Metro Area | C14: No reliable Zillow alias found
A15: Slidell-Mandeville-Covington, LA Metro Area | C15: No reliable Zillow alias found
A16: Waterbury-Shelton, CT Metro Area | C16: No reliable Zillow alias found
A17: Wildwood-The Villages, FL Metro Area | B17: The Villages, FL | C17: Strong alias candidate — verify
